aiovideo/__init__.py
aiovideo-0.2.dist-info/METADATA
aiovideo-0.2.dist-info/WHEEL
aiovideo-0.2.dist-info/top_level.txt
aiovideo-0.2.dist-info/RECORD
