Metadata-Version: 2.1
Name: aiovideo
Version: 0.2
Summary: This library used for download videos from Youtube platform!
Home-page: UNKNOWN
License: UNKNOWN
Platform: UNKNOWN
